auto_version/__init__.py
auto_version/__main__.py
auto_version/__version__.py
auto_version/auto_version_tool.py
auto_version/cli.py
auto_version/config.py
auto_version/definitions.py
auto_version/replacement_handler.py
auto_version/utils.py
auto_version/tests/__init__.py
auto_version/tests/double_target.toml
auto_version/tests/example.py
auto_version/tests/example.toml
auto_version/tests/example2.py
auto_version/tests/simple.toml
auto_version/tests/test_autoversion.py
pyautoversion-2.0.1.dist-info/LICENSE
pyautoversion-2.0.1.dist-info/METADATA
pyautoversion-2.0.1.dist-info/WHEEL
pyautoversion-2.0.1.dist-info/entry_points.txt
pyautoversion-2.0.1.dist-info/top_level.txt
pyautoversion-2.0.1.dist-info/RECORD
