Metadata-Version: 2.1
Name: pyautoversion
Version: 2.0.1
Summary: Tool for managing SemVer versioning of a project.
Home-page: https://github.com/ARMmbed/autoversion
Author: David Hyman, Arm Mbed
Author-email: support@mbed.com
License: Apache 2.0
Platform: UNKNOWN
Requires-Dist: toml
Requires-Dist: semver (~=2.13)
Requires-Dist: six
